cutetext/__init__.py
cutetext/consts.py
cutetext/converters.py
cutetext/factory.py
cutetext/maps.py
cutetext-0.0.3.dist-info/METADATA
cutetext-0.0.3.dist-info/WHEEL
cutetext-0.0.3.dist-info/licenses/LICENSE
cutetext-0.0.3.dist-info/RECORD
