Metadata-Version: 2.1
Name: cutetext
Version: 0.0.3
Summary: Package to convert text to fanct text types
Project-URL: Homepage, https://github.com/niranjanneeru/cute-text
Project-URL: Bug Tracker, https://github.com/niranjanneeru/cute-text/issues
Project-URL: Source, https://github.com/niranjanneeru/cute-text
Author-email: Niranjan B <niranjannb7777@gmail.com>
License-File: LICENSE
Classifier: License :: OSI Approved :: MIT License
Classifier: Operating System :: OS Independent
Classifier: Programming Language :: Python :: 3
Requires-Python: >=3.7
Provides-Extra: tests
Requires-Dist: pytest; extra == 'tests'
Requires-Dist: pytest-cov; extra == 'tests'
